PoBExporter/__init__.py
PoBExporter/_create_export.py
PoBExporter/_fetch.py
PoBExporter/_item.py
PoBExporter/_passive_encode.py
PoBExporter/_schema.py
PoBExporter/poe_data/gems.json
PoBExporter/poe_data/skilltree.json
PoBExporter-3.25.14.dist-info/METADATA
PoBExporter-3.25.14.dist-info/WHEEL
PoBExporter-3.25.14.dist-info/top_level.txt
PoBExporter-3.25.14.dist-info/RECORD
